{
  "type": "FeatureCollection",
  "features": [
    {
      "type": "Feature",
      "geometry": {
        "type": "Point",
        "coordinates": [
          121.532974,
          25.06315
        ]
      },
      "properties": {
        "violation_id": 110,
        "violation_date": "2025-01-09",
        "violation_time": "08:45:00",
        "device_id": "D123",
        "speed_limit": 60,
        "vehicle_speed": 75,
        "license_plate": "ATA-3596",
        "licenseplate_reply_date": "2025-01-09",
        "licenseplate_reply_time": "19:11:36",
        "vehicle_type": "機車",
        "status_code": 0,
        "district": "中山區",
        "address": "臺北市中山區松江路374號"
      }
    },
    {
      "type": "Feature",
      "geometry": {
        "type": "Point",
        "coordinates": [
          121.549297,
          25.046914
        ]
      },
      "properties": {
        "violation_id": 111,
        "violation_date": "2025-01-09",
        "violation_time": "08:00:00",
        "device_id": "D123",
        "speed_limit": 70,
        "vehicle_speed": 95,
        "license_plate": "BBD-3979",
        "licenseplate_reply_date": "2025-01-09",
        "licenseplate_reply_time": "19:11:44",
        "vehicle_type": "Not registered",
        "status_code": 27,
        "district": "松山區",
        "address": "臺北市松山區敦化南路一段7號"
      }
    }
  ]
}